{"generated_at":"2026-04-29T00:39:15.188440","series":[{"games":[{"champion":"JarvanIV","first_clear":{"camps_in_clear":6,"clear_end_ms":188001,"clear_end_str":"03:08","first_back_ms":188001,"first_back_str":"03:08","first_combat_ms":null,"first_combat_time":null,"first_combat_type":null,"full_clear":true,"route":["Red","Krugs","Raptors","Wolves","Gromp","Blue"],"route_str":"Red -> Krugs -> Raptors -> Wolves -> Gromp -> Blue","start_side":"red_start"},"first_epic":{"time_ms":714621,"time_str":"11:54","type":"dragon"},"first_gank":{"path_num":2,"time_ms":191408,"time_str":"03:11","type":"assist"},"first_scuttler":{"time_ms":231152,"time_str":"03:51"},"game_num":1,"objectives_summary":{"camps":26,"dragons":1,"scuttlers":5},"player":"CKZ behave","series_label":"CITA Kaizen vs BRUTE 17 04 2026","side":"red","total_assists":3,"total_camps":26,"total_kills":2,"total_paths":4},{"champion":"LeeSin","first_clear":{"camps_in_clear":8,"clear_end_ms":257024,"clear_end_str":"04:17","first_back_ms":257024,"first_back_str":"04:17","first_combat_ms":216809,"first_combat_time":"03:36","first_combat_type":"kill","full_clear":false,"route":["Blue","Gromp","Wolves","Raptors","Red","Krugs","Scuttler","Scuttler"],"route_str":"Blue -> Gromp -> Wolves -> Raptors -> Red -> Krugs -> Scuttler -> Scuttler","start_side":"blue_start"},"first_epic":{"time_ms":446028,"time_str":"07:26","type":"dragon"},"first_gank":{"path_num":1,"time_ms":216809,"time_str":"03:36","type":"kill"},"first_scuttler":{"time_ms":193994,"time_str":"03:13"},"game_num":2,"objectives_summary":{"camps":23,"dragons":2,"scuttlers":4,"voidgrubs":3},"player":"CKZ behave","series_label":"CITA Kaizen vs BRUTE 17 04 2026","side":"blue","total_assists":5,"total_camps":23,"total_kills":13,"total_paths":5}],"label":"CITA Kaizen vs BRUTE 17 04 2026","source_file":"d:\\f\\CITAKaizen\\output\\CITA_Kaizen_vs_BRUTE_17-04-2026\\series_jungle_pathing.html","total_games":2},{"games":[{"champion":"XinZhao","first_clear":{"camps_in_clear":6,"clear_end_ms":264033,"clear_end_str":"04:24","first_back_ms":264033,"first_back_str":"04:24","first_combat_ms":179389,"first_combat_time":"02:59","first_combat_type":"assist","full_clear":false,"route":["Blue","Gromp","Wolves","Raptors","Red","Scuttler"],"route_str":"Blue -> Gromp -> Wolves -> Raptors -> Red -> Scuttler","start_side":"blue_start"},"first_epic":{"time_ms":423328,"time_str":"07:03","type":"dragon"},"first_gank":{"path_num":1,"time_ms":179389,"time_str":"02:59","type":"assist"},"first_scuttler":{"time_ms":256853,"time_str":"04:16"},"game_num":1,"objectives_summary":{"camps":21,"dragons":3,"rift_herald":1,"scuttlers":4,"voidgrubs":3},"player":"CKZ behave","series_label":"CITA Kaizen vs EXILE esports 16 04 2026","side":"blue","total_assists":8,"total_camps":21,"total_kills":3,"total_paths":7},{"champion":"Vi","first_clear":{"camps_in_clear":6,"clear_end_ms":198004,"clear_end_str":"03:18","first_back_ms":198004,"first_back_str":"03:18","first_combat_ms":195800,"first_combat_time":"03:15","first_combat_type":"assist","full_clear":false,"route":["Red","Krugs","Raptors","Wolves","Gromp","Blue"],"route_str":"Red -> Krugs -> Raptors -> Wolves -> Gromp -> Blue","start_side":"red_start"},"first_epic":{"time_ms":358491,"time_str":"05:58","type":"dragon"},"first_gank":{"path_num":1,"time_ms":195800,"time_str":"03:15","type":"assist"},"first_scuttler":{"time_ms":247005,"time_str":"04:07"},"game_num":2,"objectives_summary":{"camps":22,"dragons":2,"scuttlers":2,"voidgrubs":3},"player":"CKZ behave","series_label":"CITA Kaizen vs EXILE esports 16 04 2026","side":"red","total_assists":3,"total_camps":22,"total_kills":3,"total_paths":10}],"label":"CITA Kaizen vs EXILE esports 16 04 2026","source_file":"d:\\f\\CITAKaizen\\output\\CITA_Kaizen_vs_EXILE_esports_16-04-2026\\series_jungle_pathing.html","total_games":2}],"summary":{"avg_gank_ms":195851,"avg_gank_str":"03:15","avg_scuttler_ms":232251,"avg_scuttler_str":"03:52","blue_starts":2,"champ_frequency":{"JarvanIV":1,"LeeSin":1,"Vi":1,"XinZhao":1},"full_clears":1,"red_starts":2,"route_frequency":{"Blue -> Gromp -> Wolves -> Raptors -> Red -> Krugs -> Scuttler -> Scuttler":1,"Blue -> Gromp -> Wolves -> Raptors -> Red -> Scuttler":1,"Red -> Krugs -> Raptors -> Wolves -> Gromp -> Blue":2}},"total_games":4,"total_series":2}
